src/__init__.py
src/calculate_values.py
ripe_calc_api-0.1.dist-info/LICENSE.txt
ripe_calc_api-0.1.dist-info/METADATA
ripe_calc_api-0.1.dist-info/WHEEL
ripe_calc_api-0.1.dist-info/top_level.txt
ripe_calc_api-0.1.dist-info/RECORD
