Metadata-Version: 2.1
Name: ripe-calc-api
Version: 0.1
Summary: Basic Calculator
Home-page: UNKNOWN
Author: Rizwan
Author-email: md1994rijwan@gmail.com
License: UNKNOWN
Platform: UNKNOWN
Classifier: Programming Language :: Python :: 3
Classifier: License :: OSI Approved :: MIT License
Classifier: Operating System :: OS Independent
